LICENSE
MANIFEST.in
README.md
README.rst
setup.py
repeat_queries/__init__.py
repeat_queries/admin.py
repeat_queries/apps.py
repeat_queries/middleware.py
repeat_queries/models.py
repeat_queries/recorder.py
repeat_queries/tests.py
repeat_queries/urls.py
repeat_queries/utils.py
repeat_queries/views.py
repeat_queries/migrations/0001_initial.py
repeat_queries/migrations/0002_auto_20181117_2241.py
repeat_queries/migrations/0003_sqlquery_duplication_count.py
repeat_queries/migrations/0004_auto_20181117_2306.py
repeat_queries/migrations/0005_sqlquery_similar_count.py
repeat_queries/migrations/0006_sqlquery_uuid.py
repeat_queries/migrations/__init__.py
repeat_queries/templates/sql.html
smart_queries.egg-info/PKG-INFO
smart_queries.egg-info/SOURCES.txt
smart_queries.egg-info/dependency_links.txt
smart_queries.egg-info/requires.txt
smart_queries.egg-info/top_level.txt